<?xml version='1.1' encoding='UTF-8'?>
<fingerprint>
  <timestamp>2022-08-09 10:32:48.366 UTC</timestamp>
  <md5sum>c6086ad2c48627941e98ba282ea5bc0d</md5sum>
  <fileName>Credential id=b0ec9864-638c-4992-9eb8-9159e1ad8ac9 name=ec2-user</fileName>
  <usages/>
  <facets>
    <com.cloudbees.plugins.credentials.fingerprints.NodeCredentialsFingerprintFacet plugin="credentials@1139.veb_9579fca_33b_">
      <timestamp>1660042539170</timestamp>
      <nodeName>slave1-c</nodeName>
      <timestamp0>1660042345367</timestamp0>
    </com.cloudbees.plugins.credentials.fingerprints.NodeCredentialsFingerprintFacet>
  </facets>
</fingerprint>